pyprefs.py
pyprefs-1.0.9.dist-info/METADATA
pyprefs-1.0.9.dist-info/WHEEL
pyprefs-1.0.9.dist-info/RECORD
